<?xml version="1.0" encoding="utf-8"?>
<!DOCTYPE hibernate-mapping PUBLIC "-//Hibernate/Hibernate Mapping DTD 3.0//EN"
"http://hibernate.sourceforge.net/hibernate-mapping-3.0.dtd">
<!-- 
    Mapping file autogenerated by MyEclipse Persistence Tools
-->
<hibernate-mapping>
    <class name="com.softline.entity.HhUsers" table="hh_users">
        <id name="id" type="integer">
            <column name="id" />
            <generator class="identity" />
        </id>
        <property name="vcEmployeeId" type="string">
            <column name="vcEmployeeID" length="50" not-null="true">
                <comment>员工编号</comment>
            </column>
        </property>
        <property name="nnodeId" type="string">
            <column name="nNodeID" length="20">
                <comment>所属机构ID</comment>
            </column>
        </property>
        <property name="vcName" type="string">
            <column name="vcName" length="50">
                <comment>姓名</comment>
            </column>
        </property>
        <property name="vcAccount" type="string">
            <column name="vcAccount" length="50">
                <comment>账号</comment>
            </column>
        </property>
        <property name="csex" type="string">
            <column name="cSex" length="20">
                <comment>性别</comment>
            </column>
        </property>
        <property name="cflag" type="string">
            <column name="cFlag" length="20">
                <comment>是否在岗、在职标示</comment>
            </column>
        </property>
        <property name="doperatorDate" type="string">
            <column name="dOperatorDate" length="20">
                <comment>操作时间</comment>
            </column>
        </property>
        <property name="vcOrganId" type="string">
            <column name="vcOrganID" length="100">
                <comment>机构节点编号</comment>
            </column>
        </property>
        <property name="vcFullName" type="string">
            <column name="vcFullName" length="100">
                <comment>机构全称</comment>
            </column>
        </property>
        <property name="nadminLevelId" type="string">
            <column name="nAdminLevelID" length="20">
                <comment>管理级别编号</comment>
            </column>
        </property>
        <property name="vcAdminLevelName" type="string">
            <column name="vcAdminLevelName" length="20">
                <comment>管理级别名称</comment>
            </column>
        </property>
        <property name="cifManageLeader" type="string">
            <column name="cIfManageLeader" length="20">
                <comment>是否是管理干部</comment>
            </column>
        </property>
        <property name="tbLNNodeId" type="string">
            <column name="tbL_nNodeID" length="20">
                <comment>所属公司编号</comment>
            </column>
        </property>
        <property name="vcName1" type="string">
            <column name="vcName1" length="100">
                <comment>机构名称</comment>
            </column>
        </property>
        <property name="vcSecondName" type="string">
            <column name="vcSecondName" length="100">
                <comment>别名</comment>
            </column>
        </property>
         <property name="createDate" type="java.lang.String">
            <column name="createDate" length="50">
                <comment>创建时间</comment>
            </column>
        </property>
        <property name="createPersonId" type="java.lang.String">
            <column name="createPersonID" length="50">
                <comment>创建人ID</comment>
            </column>
        </property>
        <property name="createPersonName" type="java.lang.String">
            <column name="createPersonName" length="50">
                <comment>创建人名</comment>
            </column>
        </property>
        <property name="lastModifyPersonId" type="java.lang.String">
            <column name="lastModifyPersonId" length="50">
                <comment>最后修改人ID</comment>
            </column>
        </property>
        <property name="lastModifyPersonName" type="java.lang.String">
            <column name="lastModifyPersonName" length="50">
                <comment>最后修改人名</comment>
            </column>
        </property>
        <property name="lastModifyDate" type="java.lang.String">
            <column name="lastModifyDate" length="50">
                <comment>最后修改时间</comment>
            </column>
        </property>
        <property name="isOut" type="java.lang.Boolean">
            <column name="isOut" >
                <comment>是否是外部人员</comment>
            </column>
        </property>
        <!--  <property name="PersontypeName" type="java.lang.String" formula="(select s.description from hh_base s where s.id= Persontype )">
            <column name="PersontypeName" >
                <comment>外部人员类别</comment>
            </column>
        </property> -->
        <property name="Persontype" type="java.lang.Integer">
            <column name="Persontype" >
                <comment>外部人员类别</comment>
            </column>
        </property>
        <property name="password" type="java.lang.String">
            <column name="password" >
                <comment>密码</comment>
            </column>
        </property>
        <!-- <property name="isallocate" formula="(select COUNT(1) from hh_usersrole s where s.usersId =vcEmployeeID limit 1 )"></property>
        <property name="isbusiness" formula="(select COUNT(1) from hh_userscompanybusiness s where s.vcEmployeeID =vcEmployeeID limit 1 )"></property>
        <property name="isSystem" formula="(select 1 from hh_userscompanybusiness s where s.vcEmployeeID =vcEmployeeID and s.is_system = 1 limit 0,1 )"></property> -->
    </class>
</hibernate-mapping>
