<?xml version="1.0" encoding="utf-8"?>
<!DOCTYPE hibernate-mapping PUBLIC "-//Hibernate/Hibernate Mapping DTD 3.0//EN"
"http://hibernate.sourceforge.net/hibernate-mapping-3.0.dtd">
<!-- 
    Mapping file autogenerated by MyEclipse Persistence Tools
-->
<hibernate-mapping>
    <class name="com.softline.entity.ReportNonInvestmentExpenditure" table="report_non_investment_expenditure" >
        <id name="id" type="java.lang.Integer">
            <column name="id" />
            <generator class="identity" />
        </id>
        <property name="year" type="java.lang.Integer">
            <column name="year" not-null="true" />
        </property>
        <property name="month" type="java.lang.Integer">
            <column name="month">
                <comment>月份</comment>
            </column>
        </property>
        <property name="org" type="java.lang.String">
            <column name="org" length="10" not-null="true">
                <comment>机构编号</comment>
            </column>
        </property>
        <property name="orgname" type="java.lang.String">
            <column name="orgname" not-null="true">
                <comment>机构名称</comment>
            </column>
        </property>
        <property name="investmentEnterpriseName" type="java.lang.String">
            <column name="investment_enterprise_name">
                <comment>投资企业名称</comment>
            </column>
        </property>
        <property name="costCategory" type="java.lang.Integer">
            <column name="cost_category">
                <comment>费用类别</comment>
            </column>
        </property>
        <property name="investmentAmount" type="java.lang.String">
            <column name="investment_amount" length="30">
                <comment>投资金额(万)</comment>
            </column>
        </property>
        <property name="domesticOverseas" type="java.lang.Integer">
            <column name="domestic_overseas">
                <comment>境内/境外</comment>
            </column>
        </property>
        <property name="projectIndustry" type="java.lang.String">
            <column name="project_industry" length="100">
                <comment>项目所属行业</comment>
            </column>
        </property>
        <property name="investmentArea" type="java.lang.String">
            <column name="investment_area" length="100">
                <comment>投资地区</comment>
            </column>
        </property>
        <property name="status" type="java.lang.Integer">
            <column name="status" not-null="true">
                <comment>审核状态</comment>
            </column>
        </property>
        <property name="isdel" type="java.lang.Integer">
            <column name="isdel" not-null="true">
                <comment>是否被删除</comment>
            </column>
        </property>
        <property name="createPersonName" type="java.lang.String">
            <column name="createPersonName" length="50">
                <comment>创建人</comment>
            </column>
        </property>
        <property name="createPersonId" type="java.lang.String">
            <column name="createPersonID" length="50">
                <comment>创建人ID</comment>
            </column>
        </property>
        <property name="createDate" type="java.lang.String">
            <column name="createDate" length="50">
                <comment>创建时间</comment>
            </column>
        </property>
        <property name="lastModifyPersonId" type="java.lang.String">
            <column name="lastModifyPersonID" length="50">
                <comment>最后修改人ID</comment>
            </column>
        </property>
        <property name="lastModifyPersonName" type="java.lang.String">
            <column name="lastModifyPersonName" length="50">
                <comment>最后修改人名</comment>
            </column>
        </property>
        <property name="lastModifyDate" type="java.lang.String">
            <column name="lastModifyDate" length="50">
                <comment>最后修改时间</comment>
            </column>
        </property>
        <property name="reportPersonName" type="java.lang.String">
            <column name="reportPersonName" length="50">
                <comment>上报人姓名</comment>
            </column>
        </property>
        <property name="reportPersonId" type="java.lang.String">
            <column name="reportPersonId" length="50">
                <comment>上报人id</comment>
            </column>
        </property>
        <property name="reportDate" type="java.lang.String">
            <column name="reportDate" length="50">
                <comment>上报时间</comment>
            </column>
        </property>
        <property name="auditorPersonName" type="java.lang.String">
            <column name="auditorPersonName" length="50">
                <comment>审核人名</comment>
            </column>
        </property>
        <property name="auditorPersonId" type="java.lang.String">
            <column name="auditorPersonId" length="50">
                <comment>审核人ID</comment>
            </column>
        </property>
        <property name="auditorDate" type="java.lang.String">
            <column name="auditorDate" length="50">
                <comment>审核时间</comment>
            </column>
        </property>
        <property name="parentorg" type="java.lang.Integer">
            <column name="parentorg">
                <comment>父机构</comment>
            </column>
        </property>
    </class>
</hibernate-mapping>
